{"G49KcvAwNjm42UauJDJqKA==":"mbr-1920x1280.jpg","wU7r79ieHs+5ByJK9xrbbg==":"project-wedding-1076x626.png","LoV8dBT9tkno3fvldqXMZg==":"project-wedding-1-1076x626.png","tOiHtsz97u34eVmK9Fomxw==":"project-best-coffee-shop-1076x440.png","R5CJSVXsZBUWwsrO5i7jzw==":"project-best-coffee-shop-1-1076x440.png","IsKJUJB1IWGPAWHUE/huLg==":"project-best-coffee-shop-2-1076x440.png","zCjI9Xg7PbNFK7Di9iVZTA==":"project-best-coffee-shop-3-1076x440.png","qmvJQ9N7FGSOtJytWSx8Xw==":"project-portfolio-1076x552.png","CIPXyaNUY5yz3PjL1eHaJw==":"kids-daycare-project-1076x605.png","Q8hQyR0axb7AbaUMopgtYg==":"kids-daycare-project-1-1076x605.png","je3sDLuUHhITj6MXREXtgA==":"mbr-320x320.png","CFYxuXiRYuxu7pa7JWFu4w==":"mbr-320x180.jpg","mlMVzEVB7oneWrWpnVgr3g==":"mbr-320x213.png","Pym8ac8Stppp3a7GL+vxvg==":"mbr-320x224.png","ldNQGeKX68im9mrkN1r/fQ==":"mbr-320x229.png","L1WS2MTkOZa8+4wS5DbQVw==":"project-wedding-1046x608.png","dqCWzlqk7RYdLjaGdQ+fcQ==":"kids-daycare-project-1046x588.png","QuaTD5t9m1tpBmXFE1F/NA==":"project-best-coffee-shop-1046x428.png","R7CiB0e7RDbG0Qu1vqxBbA==":"project-wedding-1-1046x608.png","tAGJgh6e9bSfZCjKGUYuCQ==":"kids-daycare-project-1-1046x588.png","XzDBW3DWi/sAy0DUW6apig==":"randompassword-1046x621.png","ZKU7w+bfNXenUJO+tsUxqA==":"randompassword-1-1046x621.png","TZfF4FEPWW7EKHvvu6hZ7g==":"randompassword-2-1046x621.png","PJAv8uliZI7HpihdX/nBPQ==":"randompassword-3-1046x621.png","xqBZ+M41e2yE5R+DHFypow==":"project-best-coffee-shop-1-1046x428.png"}